SplitNetwork/main.py
SplitNetwork/Structure.py
splitnetwork-1.0.0.dist-info/WHEEL
splitnetwork-1.0.0.dist-info/METADATA
splitnetwork-1.0.0.dist-info/RECORD
