Metadata-Version: 2.1
Name: splitnetwork
Version: 1.0.0
Summary: split the network
License: GPL 3.0
Author: DynJax
Author-email: devinceding@qq.com
Requires-Python: >=3.7,<4.0
Classifier: License :: Other/Proprietary License
Classifier: Programming Language :: Python :: 3
Classifier: Programming Language :: Python :: 3.7
Classifier: Programming Language :: Python :: 3.8
Classifier: Programming Language :: Python :: 3.9
Classifier: Programming Language :: Python :: 3.10
Classifier: Programming Language :: Python :: 3.11
Requires-Dist: prettytable (>=3.5.0,<4.0.0)
